{"data":{"site":{"siteMetadata":{"title":"Gatsby Starter Blog","author":"Kyle Mathews"}},"markdownRemark":{"id":"5feb453d-9c81-5335-8b0c-6e76b4dda4a0","html":"<p>This is my first post on my new fake blog! How exciting!</p>\n<p>I’m sure I’ll write a lot more interesting things in the future.</p>\n<p>Oh, and here’s a great quote from this Wikipedia on\n<a href=\"http://en.wikipedia.org/wiki/Salted_duck_egg\">salted duck eggs</a>.</p>","frontmatter":{"title":"React Demo","date":"May 01, 2015"}}},"pageContext":{"slug":"/react-demo/","previous":null,"next":{"fields":{"slug":"/test-for-test/"},"frontmatter":{"title":"Test for Test"}}}}